django_online_users-0.1.dist-info/DESCRIPTION.rst
django_online_users-0.1.dist-info/METADATA
django_online_users-0.1.dist-info/metadata.json
django_online_users-0.1.dist-info/RECORD
django_online_users-0.1.dist-info/top_level.txt
django_online_users-0.1.dist-info/WHEEL
online_users/__init__.py
online_users/admin.py
online_users/middleware.py
online_users/models.py
online_users/migrations/0001_initial.py
online_users/migrations/__init__.py
online_users/tests/__init__.py
online_users/tests/test_middleware.py
online_users/tests/test_models.py
